{
  "Name": "Blizzard effect becomes rain-like",
  "Scripts": [
    {
      "Name": "",
      "Script": "\n99B2A: 00 00\n99BCA: FF F0\n",
      "Type": "TweakScript",
      "Description": "",
      "References": [],
      "ID": null
    }
  ],
  "Version": "1.0.0.0",
  "MinVersion": "1.0.0.0",
  "MaxVersion": "0.0.0.0",
  "Description": "Makes the unused 'Blizzard' environmental effect act more like rain would. Texture location is at DA90BC. By hamius8000",
  "EmbeddedFiles": {
    "CompressedFiles": {}
  },
  "ID": null
}